random_event/__init__.py
random_event/errors.py
Random_Event-0.2.dist-info/LICENSE
Random_Event-0.2.dist-info/METADATA
Random_Event-0.2.dist-info/WHEEL
Random_Event-0.2.dist-info/top_level.txt
Random_Event-0.2.dist-info/RECORD
