Metadata-Version: 2.1
Name: Random-Event
Version: 0.2
Summary: A python module made to generate random event at almost random time
Home-page: https://github.com/mossyegghead01/random-event
Author: mossyegghead01
License: MIT
Project-URL: Documentation, https://random-event.readthedocs.io/en/stable/
Platform: UNKNOWN
Requires-Dist: schedule
